namedex/__init__.py
namedex/namedex.py
namedex-0.1.11.dist-info/AUTHORS.rst
namedex-0.1.11.dist-info/LICENSE
namedex-0.1.11.dist-info/METADATA
namedex-0.1.11.dist-info/WHEEL
namedex-0.1.11.dist-info/top_level.txt
namedex-0.1.11.dist-info/RECORD
