Metadata-Version: 2.1
Name: namedex
Version: 0.1.11
Summary: An implementation of the soundex algorithm.
Home-page: https://github.com/JoelMon/namedex
Author: Joel Montes de Oca
Author-email: JoelMontes01@gmail.com
License: GNU General Public License v3
Keywords: namedex
Platform: UNKNOWN
Classifier: Development Status :: 5 - Production/Stable
Classifier: Intended Audience :: Developers
Classifier: License :: OSI Approved :: GNU General Public License v3 (GPLv3)
Classifier: Natural Language :: English
Classifier: Programming Language :: Python :: 3
Classifier: Programming Language :: Python :: 3.5
Classifier: Programming Language :: Python :: 3.6
Classifier: Programming Language :: Python :: 3.7
